setup.cfg
setup.py
NewEncSajad.egg-info/PKG-INFO
NewEncSajad.egg-info/SOURCES.txt
NewEncSajad.egg-info/dependency_links.txt
NewEncSajad.egg-info/top_level.txt
SajadCrypto/__init__.py