Metadata-Version: 2.1
Name: NewEncSajad
Version: 1
Summary: an encryption library for sajad
Author: NewEncSajad
Classifier: Programming Language :: Python :: 3
